katpoint/__init__.py
katpoint/antenna.py
katpoint/catalogue.py
katpoint/conversion.py
katpoint/delay.py
katpoint/ephem_extra.py
katpoint/flux.py
katpoint/model.py
katpoint/pointing.py
katpoint/projection.py
katpoint/refraction.py
katpoint/target.py
katpoint/timestamp.py
katpoint/test/__init__.py
katpoint/test/test_antenna.py
katpoint/test/test_catalogue.py
katpoint/test/test_conversion.py
katpoint/test/test_delay.py
katpoint/test/test_flux.py
katpoint/test/test_model.py
katpoint/test/test_pointing.py
katpoint/test/test_projection.py
katpoint/test/test_refraction.py
katpoint/test/test_target.py
katpoint/test/test_timestamp.py
katpoint-0.10.2.dist-info/LICENSE.txt
katpoint-0.10.2.dist-info/METADATA
katpoint-0.10.2.dist-info/WHEEL
katpoint-0.10.2.dist-info/top_level.txt
katpoint-0.10.2.dist-info/RECORD
