Metadata-Version: 2.1
Name: katpoint
Version: 0.10.2
Summary: Karoo Array Telescope pointing coordinate library
Home-page: https://github.com/ska-sa/katpoint
Author: Ludwig Schwardt
Author-email: ludwig@ska.ac.za
License: Modified BSD
Keywords: meerkat ska
Platform: OS Independent
Classifier: Development Status :: 5 - Production/Stable
Classifier: Intended Audience :: Developers
Classifier: License :: OSI Approved :: BSD License
Classifier: Operating System :: OS Independent
Classifier: Programming Language :: Python
Classifier: Programming Language :: Python :: 2
Classifier: Programming Language :: Python :: 2.7
Classifier: Programming Language :: Python :: 3
Classifier: Programming Language :: Python :: 3.3
Classifier: Programming Language :: Python :: 3.4
Classifier: Programming Language :: Python :: 3.5
Classifier: Programming Language :: Python :: 3.6
Classifier: Programming Language :: Python :: 3.7
Classifier: Programming Language :: Python :: 3.8
Classifier: Programming Language :: Python :: 3.9
Classifier: Programming Language :: Python :: 3.10
Classifier: Programming Language :: Python :: 3.11
Classifier: Programming Language :: Python :: 3.12
Classifier: Programming Language :: Python :: 3.13
Classifier: Topic :: Software Development :: Libraries :: Python Modules
Classifier: Topic :: Scientific/Engineering :: Astronomy
Requires-Python: >=2.7, !=3.0.*, !=3.1.*, !=3.2.*, <4
License-File: LICENSE.txt
Requires-Dist: future
Requires-Dist: numpy
Requires-Dist: ephem
